MANIFEST.in
README.md
setup.py
dj_paystack/__init__.py
dj_paystack/admin.py
dj_paystack/apps.py
dj_paystack/models.py
dj_paystack/tests.py
dj_paystack/views.py
dj_paystack.egg-info/PKG-INFO
dj_paystack.egg-info/SOURCES.txt
dj_paystack.egg-info/dependency_links.txt
dj_paystack.egg-info/requires.txt
dj_paystack.egg-info/top_level.txt