Metadata-Version: 1.0
Name: dj-paystack
Version: 0.1
Summary: Paystack for Django
Home-page: https://github.com/ebinabo/dj-paystack/
Author: ebinabo
Author-email: edgarjohn95@gmail.com
License: MIT
Platform: UNKNOWN
